[{"model": "survey.survey", "pk": 1, "fields": {"question": "Тест 1", "variant_a": "Ухаживать за животными", "variant_b": "Обслуживать машины, приборы (следить, регулировать)"}}, {"model": "survey.survey", "pk": 2, "fields": {"question": "Тест 2", "variant_a": "Помогать больным", "variant_b": "Составлять таблицы, схемы, программы для вычислительных машин"}}, {"model": "survey.survey", "pk": 3, "fields": {"question": "Тест 3", "variant_a": "Следить за качеством книжных иллюстраций, плакатов, художественных открыток, грампластинок", "variant_b": "Следить за состоянием, развитием растений"}}, {"model": "survey.survey", "pk": 4, "fields": {"question": "Тест 4", "variant_a": "Обрабатывать материалы (дерево, ткань, металл, пластмассу и т.п.)", "variant_b": "Доводить Товары до потребителя, рекламировать, продавать"}}, {"model": "survey.survey", "pk": 5, "fields": {"question": "Тест 5", "variant_a": "Обсуждать научно-популярные книги, статьи", "variant_b": "Обсуждать художественные книги (или пьесы, концерты)"}}, {"model": "survey.survey", "pk": 6, "fields": {"question": "Тест 6", "variant_a": "Выращивать молодняк (животных какой-либо породы)", "variant_b": "Тренировать товарищей (или младших) в выполнении каких-либо действий (трудовых, учебных, спортивных)"}}, {"model": "survey.survey", "pk": 7, "fields": {"question": "Тест 7", "variant_a": "Копировать рисунки, изображения (или настраивать музыкальные инструменты) ", "variant_b": "Управлять каким-либо грузовым (подъемным или транспортным) средством – подъемным краном, трактором, тепловозом и др."}}, {"model": "survey.survey", "pk": 8, "fields": {"question": "Тест 8", "variant_a": "Сообщать, разъяснять людям нужные им сведения (в справочном бюро, на экскурсии и т.д.) ", "variant_b": "Оформлять выставки, витрины (или участвовать в подготовке пьес, концертов)"}}, {"model": "survey.survey", "pk": 9, "fields": {"question": "Тест 9", "variant_a": "Ремонтировать вещи, изделия (одежду, технику), жилище", "variant_b": "Искать и исправлять ошибки в текстах, таблицах, рисунках"}}, {"model": "survey.survey", "pk": 10, "fields": {"question": "Тест 10", "variant_a": "Лечить животных", "variant_b": "Выполнять вычисления, расчеты"}}, {"model": "survey.survey", "pk": 11, "fields": {"question": "Тест 11", "variant_a": "Выводить новые сорта растений", "variant_b": "Конструировать, проектировать новые виды промышленных изделий (машины, одежду, дома, продукты питания и т.п.)"}}, {"model": "survey.survey", "pk": 12, "fields": {"question": "Тест 12", "variant_a": "Разбирать споры, ссоры между людьми, убеждать, разъяснять, наказывать, поощрять ", "variant_b": "Разбираться в чертежах, схемах, таблицах (проверять, уточнять, приводить в порядок)"}}, {"model": "survey.survey", "pk": 13, "fields": {"question": "Тест 13", "variant_a": "Наблюдать, изучать работу кружков художественной самодеятельности", "variant_b": "Наблюдать, изучать жизнь микробов"}}, {"model": "survey.survey", "pk": 14, "fields": {"question": "Тест 14", "variant_a": "Обслуживать, налаживать медицинские приборы, аппараты", "variant_b": "Оказывать людям медицинскую помощь при ранениях, ушибах, ожогах и т.п."}}, {"model": "survey.survey", "pk": 15, "fields": {"question": "Тест 15", "variant_a": "Художественно описывать, изображать события (наблюдаемые и представляемые)", "variant_b": "Составлять точные описания-отчеты о наблюдаемых явлениях, событиях, измеряемых объектах и др."}}, {"model": "survey.survey", "pk": 16, "fields": {"question": "Тест 16", "variant_a": "Делать лабораторные анализы в больнице ", "variant_b": "Принимать, осматривать больных, беседовать с ними, назначать лечение"}}, {"model": "survey.survey", "pk": 17, "fields": {"question": "Тест 17", "variant_a": "Красить или расписывать стены помещений, поверхность изделий", "variant_b": "Осуществлять монтаж или сборку машин, приборов"}}, {"model": "survey.survey", "pk": 18, "fields": {"question": "Тест 18", "variant_a": "Организовать культпоходы сверстников или младших в театры, музеи, экскурсии, туристические походы и т.п.", "variant_b": "Играть на сцене, принимать участие в концертах"}}, {"model": "survey.survey", "pk": 19, "fields": {"question": "Тест 19", "variant_a": "Изготовлять по чертежам детали, изделия (машины, одежду), строить здания", "variant_b": "Заниматься черчением, копировать чертежи, карты"}}, {"model": "survey.survey", "pk": 20, "fields": {"question": "Тест 20", "variant_a": "Вести борьбу с болезнями растений, с вредителями леса, сада", "variant_b": "Работать на клавишных машинах (пишущей машинке, телетайпе, наборной машине и др.)"}}]